{"openapi":"3.0.1","info":{"title":"Component Registry API","description":"Components and profiles registry for the Component Metadata Infrastructure","contact":{"name":"CLARIN ERIC","url":"https://www.clarin.eu","email":"cmdi@clarin.eu"},"version":"1.0"},"paths":{"/rest/registry/items/{componentId}":{"get":{"operationId":"getItem","parameters":[{"name":"componentId","in":"path","required":true,"schema":{"type":"string"}}],"responses":{"default":{"description":"default response","content":{"application/json":{"schema":{"$ref":"#/components/schemas/BaseDescription"}},"application/xml":{"schema":{"$ref":"#/components/schemas/BaseDescription"}}}}}}},"/rest/registry/items/{componentId}/spec":{"get":{"operationId":"getItemSpec","parameters":[{"name":"componentId","in":"path","required":true,"schema":{"type":"string"}}],"responses":{"default":{"description":"default response","content":{"application/json":{"schema":{"$ref":"#/components/schemas/ComponentSpec"}},"application/xml":{"schema":{"$ref":"#/components/schemas/ComponentSpec"}}}}}}},"/rest/registry/items":{"get":{"operationId":"getItems","parameters":[{"name":"sortBy","in":"query","schema":{"type":"string","default":"name"}},{"name":"sortDirection","in":"query","schema":{"type":"string","default":"ASC","enum":["ASC","DESC"]}}],"responses":{"default":{"description":"default response","content":{"application/json":{"schema":{"type":"array","items":{"$ref":"#/components/schemas/BaseDescription"}}},"application/xml":{"schema":{"type":"array","items":{"$ref":"#/components/schemas/BaseDescription"}}}}}}}},"/rest/application.wadl/{path}":{"get":{"operationId":"getExternalGrammar","parameters":[{"name":"path","in":"path","required":true,"schema":{"type":"string"}}],"responses":{"default":{"description":"default response","content":{"application/xml":{}}}}}},"/rest/application.wadl":{"get":{"operationId":"getWadl","responses":{"default":{"description":"default response","content":{"application/vnd.sun.wadl+xml":{},"application/xml":{}}}}}}},"components":{"schemas":{"BaseDescription":{"type":"object","properties":{"dbId":{"type":"integer","format":"int64"},"name":{"type":"string"},"description":{"type":"string"},"registrationDate":{"type":"string","format":"date-time"},"creatorName":{"type":"string"},"dbUserId":{"type":"integer","format":"int64"},"userId":{"type":"string"},"domainName":{"type":"string"},"href":{"type":"string","xml":{"namespace":"http://www.w3.org/1999/xlink"}},"groupName":{"type":"string"},"status":{"type":"string","enum":["development","production","deprecated"]},"derivedfrom":{"type":"string"},"successor":{"type":"string"},"commentsCount":{"type":"integer","format":"int32"},"content":{"type":"string"},"deleted":{"type":"boolean"},"recommended":{"type":"boolean"},"public":{"type":"boolean"},"id":{"type":"string"},"showInEditor":{"type":"boolean"},"isPublic":{"type":"boolean"}},"xml":{"name":"description"}},"Attribute":{"type":"object","properties":{"documentation":{"type":"array","xml":{"name":"Documentation"},"items":{"$ref":"#/components/schemas/DocumentationType"}},"attributeValueScheme":{"$ref":"#/components/schemas/ValueSchemeType"},"autoValue":{"type":"array","xml":{"name":"AutoValue"},"items":{"type":"string","xml":{"name":"AutoValue"}}},"name":{"type":"string","xml":{"attribute":true}},"conceptLink":{"type":"string","xml":{"name":"ConceptLink","attribute":true}},"valueScheme":{"type":"string","xml":{"name":"ValueScheme","attribute":true},"enum":["BOOLEAN","DECIMAL","FLOAT","INT","STRING","ANY_URI","DATE","G_DAY","G_MONTH","G_YEAR","TIME","DATE_TIME"]},"required":{"type":"boolean","xml":{"name":"Required","attribute":true}},"otherAttributes":{"type":"object","additionalProperties":{"type":"string"}}}},"AttributeListType":{"required":["attribute"],"type":"object","properties":{"attribute":{"type":"array","xml":{"name":"Attribute"},"items":{"$ref":"#/components/schemas/Attribute"}}}},"ComponentSpec":{"required":["component","header"],"type":"object","properties":{"header":{"$ref":"#/components/schemas/Header"},"component":{"$ref":"#/components/schemas/ComponentType"},"isProfile":{"type":"boolean","xml":{"attribute":true}},"cmdversion":{"type":"string"},"cmdoriginalVersion":{"type":"string"}},"xml":{"name":"ComponentSpec"}},"ComponentType":{"type":"object","properties":{"documentation":{"type":"array","xml":{"name":"Documentation"},"items":{"$ref":"#/components/schemas/DocumentationType"}},"attributeList":{"$ref":"#/components/schemas/AttributeListType"},"element":{"type":"array","xml":{"name":"Element"},"items":{"$ref":"#/components/schemas/ElementType"}},"component":{"type":"array","xml":{"name":"Component"},"items":{"$ref":"#/components/schemas/ComponentType"}},"name":{"type":"string","xml":{"attribute":true}},"componentRef":{"type":"string","xml":{"name":"ComponentRef","attribute":true}},"conceptLink":{"type":"string","xml":{"name":"ConceptLink","attribute":true}},"cardinalityMin":{"type":"array","items":{"type":"string"}},"cardinalityMax":{"type":"array","items":{"type":"string"}},"base":{"type":"string","xml":{"namespace":"http://www.w3.org/XML/1998/namespace","attribute":true}},"otherAttributes":{"type":"object","additionalProperties":{"type":"string"}}}},"DocumentationType":{"type":"object","properties":{"value":{"type":"string"},"lang":{"type":"string","xml":{"namespace":"http://www.w3.org/XML/1998/namespace","attribute":true}}}},"ElementType":{"type":"object","properties":{"documentation":{"type":"array","xml":{"name":"Documentation"},"items":{"$ref":"#/components/schemas/DocumentationType"}},"attributeList":{"$ref":"#/components/schemas/AttributeListType"},"valueScheme":{"$ref":"#/components/schemas/ValueSchemeType"},"autoValue":{"type":"array","xml":{"name":"AutoValue"},"items":{"type":"string","xml":{"name":"AutoValue"}}},"name":{"type":"string","xml":{"attribute":true}},"conceptLink":{"type":"string","xml":{"name":"ConceptLink","attribute":true}},"cardinalityMin":{"type":"array","items":{"type":"string"}},"cardinalityMax":{"type":"array","items":{"type":"string"}},"multilingual":{"type":"boolean","xml":{"name":"Multilingual","attribute":true}},"otherAttributes":{"type":"object","additionalProperties":{"type":"string"}},"ValueSchemeType":{"type":"string","xml":{"name":"ValueScheme","attribute":true},"enum":["BOOLEAN","DECIMAL","FLOAT","INT","STRING","ANY_URI","DATE","G_DAY","G_MONTH","G_YEAR","TIME","DATE_TIME"]}}},"EnumerationType":{"required":["item"],"type":"object","properties":{"appinfo":{"type":"string"},"item":{"type":"array","items":{"$ref":"#/components/schemas/ItemType"}}}},"Header":{"required":["id","name","status"],"type":"object","properties":{"id":{"type":"string","xml":{"name":"ID"}},"name":{"type":"string","xml":{"name":"Name"}},"description":{"type":"string","xml":{"name":"Description"}},"status":{"type":"string","xml":{"name":"Status"}},"statusComment":{"type":"string","xml":{"name":"StatusComment"}},"successor":{"type":"string","xml":{"name":"Successor"}},"derivedFrom":{"type":"string","xml":{"name":"DerivedFrom"}}}},"ItemType":{"type":"object","properties":{"value":{"type":"string"},"conceptLink":{"type":"string","xml":{"name":"ConceptLink","attribute":true}},"appInfo":{"type":"string","xml":{"name":"AppInfo","attribute":true}},"otherAttributes":{"type":"object","additionalProperties":{"type":"string"}}}},"ValueSchemeType":{"type":"object","properties":{"pattern":{"type":"string"},"vocabulary":{"$ref":"#/components/schemas/VocabularyType"}}},"VocabularyType":{"type":"object","properties":{"enumeration":{"$ref":"#/components/schemas/EnumerationType"},"uri":{"type":"string","xml":{"name":"URI","attribute":true}},"valueProperty":{"type":"string","xml":{"name":"ValueProperty","attribute":true}},"valueLanguage":{"type":"string","xml":{"name":"ValueLanguage","attribute":true}}}}}}}